{
    "anims": [
        {
            "key": "red-coin",
            "type": "frame",
            "frames": [
                {
                    "key": "MonedaR",
                    "frame": 0,
                    "duration": 0,
                    "keyframe": false
                },
                {
                    "key": "MonedaR",
                    "frame": 1,
                    "duration": 0,
                    "keyframe": false
                },
                {
                    "key": "MonedaR",
                    "frame": 2,
                    "duration": 0,
                    "keyframe": false
                },
                {
                    "key": "MonedaR",
                    "frame": 3,
                    "duration": 0,
                    "keyframe": false
                },
                {
                    "key": "MonedaR",
                    "frame": 4,
                    "duration": 0,
                    "keyframe": false
                }
            ],
            "frameRate": 24,
            "skipMissedFrames": true,
            "repeat": -1,
            "randomFrame": false
        },
        {
            "key": "blue-coin",
            "type": "frame",
            "frames": [
                {
                    "key": "spr_coin_azu",
                    "frame": 0,
                    "duration": 0,
                    "keyframe": false
                },
                {
                    "key": "spr_coin_azu",
                    "frame": 1,
                    "duration": 0,
                    "keyframe": false
                },
                {
                    "key": "spr_coin_azu",
                    "frame": 2,
                    "duration": 0,
                    "keyframe": false
                },
                {
                    "key": "spr_coin_azu",
                    "frame": 3,
                    "duration": 0,
                    "keyframe": false
                }
            ],
            "frameRate": 10,
            "skipMissedFrames": true,
            "repeat": -1,
            "randomFrame": false
        }
    ],
    "globalTimeScale": 1,
    "meta": {
        "app": "Phaser Editor 2D v3",
        "contentType": "Phaser v3 Animations"
    },
    "settings": {
        "sourceLang": "TYPE_SCRIPT",
        "esModule": true,
        "generateCode": true
    }
}